  1           0 RESUME                   0

  2           2 LOAD_CONST               1 (0)
              4 STORE_FAST               1 (x)

  3           6 LOAD_FAST                0 (a)
              8 LOAD_CONST               1 (0)
             10 COMPARE_OP               4 (>)
             16 POP_JUMP_FORWARD_IF_FALSE     8 (to 34)
             18 LOAD_FAST                0 (a)
             20 LOAD_CONST               2 (5)
             22 COMPARE_OP               0 (<)
             28 POP_JUMP_FORWARD_IF_FALSE     2 (to 34)

  4          30 LOAD_CONST               3 (1)
             32 STORE_FAST               1 (x)

  6     >>   34 LOAD_FAST                0 (a)
             36 LOAD_CONST               3 (1)
             38 BINARY_OP                0 (+)
             42 STORE_FAST               2 (b)

  7          44 LOAD_FAST                1 (x)
             46 LOAD_CONST               3 (1)
             48 COMPARE_OP               2 (==)
             54 POP_JUMP_FORWARD_IF_FALSE     8 (to 72)
             56 LOAD_FAST                2 (b)
             58 LOAD_CONST               4 (6)
             60 COMPARE_OP               4 (>)
             66 POP_JUMP_FORWARD_IF_FALSE     2 (to 72)

  8          68 LOAD_CONST               5 (15)
             70 RETURN_VALUE

  9     >>   72 LOAD_FAST                2 (b)
             74 RETURN_VALUE
